gnu_screen_class-1.2.1.dist-info/licenses/LICENSE
gnuscreen/__init__.py
gnuscreen/main.py
test/generate_help.py
gnu_screen_class-1.2.1.dist-info/METADATA
gnu_screen_class-1.2.1.dist-info/WHEEL
gnu_screen_class-1.2.1.dist-info/entry_points.txt
gnu_screen_class-1.2.1.dist-info/top_level.txt
gnu_screen_class-1.2.1.dist-info/RECORD
