Metadata-Version: 2.4
Name: gnu-screen-class
Version: 1.2.1
Summary: wrapper around gnu screen
Author: Gerard
Author-email: gweatherby@uchc.edu
License: MIT License
Project-URL: Homepage, https://github.com/NMRhub/gnuscreen
Requires-Python: >=3.8
License-File: LICENSE
Dynamic: license-file
